main.v
module processor (clk1, clk2);

input  clk1 , clk2;   //Refers to two phase clock

reg [31:0]  PC, IF_ID_IR, IF_ID_NPC; 
// PC = Program Counter
// IF_ID_IR = Instruction register in the latch stage between the IF and ID stages
// IF_ID_NPC = New Program Counter

reg [31:0]  ID_EX_IR, ID_EX_NPC, ID_EX_A, ID_EX_B, ID_EX_Imm;
// ID_EX_IR = Instruction register in the latch stage between the ID and EX stages
// ID_EX_NPC = New program counter 
// ID_EX_A = stores value of the register for execution
// ID_EX_B = stores value of the register for execution
// ID_EX_Imm = Immediate value is sign extended to make it 32 bit 

reg [31:0]  EX_MEM_IR , EX_MEM_ALUOut, EX_MEM_B;
// EX_MEM_IR = Instruction register in the latch stage between the EX and MEM stages
// EX_MEM_ALUOut =  Temporary register to store the output of the execution
// EX_MEM_B = To store value while execution

reg [31:0]  MEM_WB_IR, MEM_WB_ALUOut, MEM_WB_LMD;
// MEM_WB_IR = Instruction register in the latch stage between the MEM and WB stages
// MEM_WB_ALUOut = Containing output of execution
// MEM_WB_LMD = To load memory

reg [2:0] ID_EX_type,EX_MEM_type,MEM_WB_type;

reg [31:0]  Reg [0:31];      // Register bank (32 ✕ 32) 32 registers each of 32 bit
reg [31:0]  Mem [0:1023];    // 1024 ✕ 32 memory , 32 bit instruction set containing information about opcode source , destination register and offset

// operation codes for operations
parameter 
ADD= 6'b000000,  //ADD =  A+ B
SUB=6'b000001,  // SUB = A-B
AND=6'b000010,   // AND = A & B
OR=6'b000011,    // OR = A|B
CMP= 6'b000100,  // CMP = A<B 
MUL=6'b000101,   // MUL = A*B

ADDI= 6'b001010, // Adding a number with a value stored in a register
SUBI = 6'b001011, // Subtracting a number from a value stored in a register
CMPI=6'b001100 , // Stores 1 if given number is less than value stored in a register 

LW=6'b001000,    // load word
SW=6'b001001,    // store word
HLT= 6'b111111,  // to halt the instruction

//type of instructions
RR_ALU= 3'b000,   // Register to register
RM_ALU = 3'b001,  // Register to memory
LOAD = 3'b010,    // Loading data from mem address to register  
STORE= 3'b011,    // Storing data from register to mem address
HALT= 3'b101;     // Halting the program

reg HALTED;       // flag set to 1 if halt detected

// IF stage
always @(posedge clk1 ) 
begin
    if(HALTED==0)
    begin    
        IF_ID_IR <= #2 Mem[PC];
        IF_ID_NPC <= PC+1; 
        PC <= #2 PC+1;     // increasing program counter to get the next instruction
    end
end

//ID stage
always @(posedge clk2 ) 
begin
    if(HALTED==0)
    begin
        if(IF_ID_IR[25:21]==5'b00000)
            begin
                ID_EX_A <= 0;
            end
        else 
            begin
                ID_EX_A <= #2 Reg[IF_ID_IR[25:21]]; 
            end

        if(IF_ID_IR[20:16]==5'b00000)
            begin
                ID_EX_B <= 0;
            end
        else
            begin
                ID_EX_B <= #2 Reg[IF_ID_IR[20:16]]; 
            end
        ID_EX_NPC <= #2 IF_ID_NPC;
        ID_EX_IR  <= #2 IF_ID_IR;
        ID_EX_Imm <= #2 {{16{IF_ID_IR[15]}},{IF_ID_IR[15:0]}};

        case (IF_ID_IR[31:26])
            ADD,SUB,AND,OR,CMP,MUL : ID_EX_type <= #2 RR_ALU;
            ADDI,SUBI,CMPI :         ID_EX_type <= #2 RM_ALU;
            LW :                     ID_EX_type <= #2 LOAD;
            SW :                     ID_EX_type <= #2 STORE;
            HLT :                    ID_EX_type <= #2 HALT;
            default :                ID_EX_type <= #2 HALT;
        endcase
    end     
end

//EX Stage
always @(posedge clk1 ) 
begin
    if(HALTED==0)
    begin
        EX_MEM_type <= #2 ID_EX_type;
        EX_MEM_IR <= #2 ID_EX_IR;
       
        case (ID_EX_type)
        RR_ALU : begin
                    case(ID_EX_IR[31:26])
                        ADD: EX_MEM_ALUOut <= #2 ID_EX_A + ID_EX_B ; 
                        SUB: EX_MEM_ALUOut <= #2 ID_EX_A - ID_EX_B ; 
                        AND: EX_MEM_ALUOut <= #2 ID_EX_A & ID_EX_B ; 
                        OR:  EX_MEM_ALUOut <= #2 ID_EX_A | ID_EX_B ; 
                        CMP: EX_MEM_ALUOut <= #2 ID_EX_A < ID_EX_B ; 
                        MUL: EX_MEM_ALUOut <= #2 ID_EX_A * ID_EX_B ; 
                        default: EX_MEM_ALUOut <= #2 32'hxxxxxxxx ; 
                    endcase
                 end
        RM_ALU : begin
                    case(ID_EX_IR[31:26])
                        ADDI : EX_MEM_ALUOut <= #2 ID_EX_A + ID_EX_Imm;
                        SUBI : EX_MEM_ALUOut <= #2 ID_EX_A - ID_EX_Imm; 
                        CMPI : EX_MEM_ALUOut <= #2 ID_EX_A < ID_EX_Imm; 
                        default : EX_MEM_ALUOut <= #2 32'hxxxxxxxx; 
                    endcase
                 end
        LOAD,STORE :
                 begin
                     EX_MEM_ALUOut <= #2 ID_EX_A +ID_EX_Imm;
                     EX_MEM_B      <= #2 ID_EX_B;
                 end
        endcase
    end 
end

//MEM Stage
always @(posedge clk2 ) 
begin
    if(HALTED==0)
    begin
       MEM_WB_type <= #2 EX_MEM_type;
       MEM_WB_IR <= #2 EX_MEM_IR;

       case (EX_MEM_type)
            RR_ALU,RM_ALU :  MEM_WB_ALUOut <= #2 EX_MEM_ALUOut ; 
            LOAD : MEM_WB_LMD <= #2 Mem[EX_MEM_ALUOut]; 
            STORE : 
                begin
                    Mem[EX_MEM_ALUOut] <= #2 EX_MEM_B; //written in memory
                end 
        endcase    
    end
end

//WB stage
always @(posedge clk1 ) 
begin
    case(MEM_WB_type)
        RR_ALU : Reg[MEM_WB_IR[15:11]] <= #2 MEM_WB_ALUOut ; //written in rd
        RM_ALU : Reg[MEM_WB_IR[20:16]] <= #2 MEM_WB_ALUOut ; //written in rt
        LOAD   : Reg[MEM_WB_IR[20:16]] <= #2 MEM_WB_LMD    ; //written in rt
        HALT   : HALTED <= #2 1'b1;                          // halt flag set to 1
    endcase
end

endmodule

main_tb_3.v
// Register to register type

module test_mips32;
    reg clk1, clk2;
    integer k;

    processor mips (clk1, clk2);

    initial begin
        clk1 = 0;
        clk2 = 0;
        repeat (20)
        begin
            #5 clk1 = 1; 
            #5 clk1 = 0;
            #5 clk2 = 1;
            #5 clk2 = 0;
        end
    end
    // adding R1,R2,R3 storing them in R5
    //-------------------------------------------------------------------------
    initial begin
        for(k = 0;k<31;k++)
            mips.Reg[k] = k;
        
        mips.Mem[0] = 32'h2801000a;   // ADDI  R1, R0, 10 => R1 = 10
        mips.Mem[1] = 32'h28020014;   // ADDI  R2, R0, 20 => R2 = 20
        mips.Mem[2] = 32'h28030019;   // ADDI  R3, R0, 25 => R3 = 25
        mips.Mem[3] = 32'h0ce77800;   // OR -- dummy instruction R7, R7, R7
        mips.Mem[4] = 32'h0ce77800;   // OR -- dummy instruction R7, R7, R7
        mips.Mem[5] = 32'h00222000;   // ADD   R4, R1, R2 => R4 = R1+R2 = 30
        mips.Mem[6] = 32'h0ce77800;   // OR -- dummy instruction
        mips.Mem[7] = 32'h00832800;   // ADD   R5, R4 , R3 => R5 = R4+R3 =55
        mips.Mem[8] = 32'hfc000000;   // HLT

        mips.HALTED = 0;
        mips.PC = 0;
        
        #280
        for(k=0;k<6;k++)begin
            $display ("R%1d - %2d", k, mips.Reg[k]);
        end
        
    end    

    initial begin
        $dumpfile ("tb_3.vcd");
        $dumpvars (0, test_mips32);
        #100000 $finish;
    end
endmodule

tb_3.vcd
$date
	Sun Nov 21 22:43:58 2021
$end
$version
	Icarus Verilog
$end
$timescale
	1s
$end
$scope module test_mips32 $end
$var reg 1 ! clk1 $end
$var reg 1 " clk2 $end
$var integer 32 # k [31:0] $end
$scope module mips $end
$var wire 1 ! clk1 $end
$var wire 1 " clk2 $end
$var reg 32 $ EX_MEM_ALUOut [31:0] $end
$var reg 32 % EX_MEM_B [31:0] $end
$var reg 32 & EX_MEM_IR [31:0] $end
$var reg 3 ' EX_MEM_type [2:0] $end
$var reg 1 ( HALTED $end
$var reg 32 ) ID_EX_A [31:0] $end
$var reg 32 * ID_EX_B [31:0] $end
$var reg 32 + ID_EX_IR [31:0] $end
$var reg 32 , ID_EX_Imm [31:0] $end
$var reg 32 - ID_EX_NPC [31:0] $end
$var reg 3 . ID_EX_type [2:0] $end
$var reg 32 / IF_ID_IR [31:0] $end
$var reg 32 0 IF_ID_NPC [31:0] $end
$var reg 32 1 MEM_WB_ALUOut [31:0] $end
$var reg 32 2 MEM_WB_IR [31:0] $end
$var reg 32 3 MEM_WB_LMD [31:0] $end
$var reg 3 4 MEM_WB_type [2:0] $end
$var reg 32 5 PC [31:0] $end
$upscope $end
$upscope $end
$enddefinitions $end
#0
$dumpvars
b0 5
bx 4
bx 3
bx 2
bx 1
bx 0
bx /
bx .
bx -
bx ,
bx +
bx *
bx )
0(
bx '
bx &
bx %
bx $
b11111 #
0"
0!
$end
#5
b1 0
1!
#7
b1 5
b101000000000010000000000001010 /
#10
0!
#15
b0 )
1"
#17
b1 .
b1010 ,
b101000000000010000000000001010 +
b1 -
b1 *
#20
0"
#25
b10 0
1!
#27
b1010 $
b101000000000010000000000001010 &
b1 '
b10 5
b101000000000100000000000010100 /
#30
0!
#35
1"
#37
b1010 1
b101000000000010000000000001010 2
b1 4
b10100 ,
b101000000000100000000000010100 +
b10 -
b10 *
#40
0"
#45
b11 0
1!
#47
b11 5
b101000000000110000000000011001 /
b10100 $
b101000000000100000000000010100 &
#50
0!
#55
1"
#57
b11001 ,
b101000000000110000000000011001 +
b11 -
b11 *
b10100 1
b101000000000100000000000010100 2
#60
0"
#65
b100 0
1!
#67
b11001 $
b101000000000110000000000011001 &
b100 5
b1100111001110111100000000000 /
#70
0!
#75
1"
#77
b11001 1
b101000000000110000000000011001 2
b0 .
b111100000000000 ,
b1100111001110111100000000000 +
b100 -
b111 *
b111 )
#80
0"
#85
b101 0
1!
#87
b101 5
b111 $
b1100111001110111100000000000 &
b0 '
#90
0!
#95
1"
#97
b101 -
b111 1
b1100111001110111100000000000 2
b0 4
#100
0"
#105
b110 0
1!
#107
b110 5
b1000100010000000000000 /
#110
0!
#115
1"
#117
b10000000000000 ,
b1000100010000000000000 +
b110 -
b10100 *
b1010 )
#120
0"
#125
b111 0
1!
#127
b111 5
b1100111001110111100000000000 /
b11110 $
b1000100010000000000000 &
#130
0!
#135
1"
#137
b111100000000000 ,
b1100111001110111100000000000 +
b111 -
b111 *
b111 )
b11110 1
b1000100010000000000000 2
#140
0"
#145
b1000 0
1!
#147
b111 $
b1100111001110111100000000000 &
b1000 5
b100000110010100000000000 /
#150
0!
#155
1"
#157
b111 1
b1100111001110111100000000000 2
b10100000000000 ,
b100000110010100000000000 +
b1000 -
b11001 *
b11110 )
#160
0"
#165
b1001 0
1!
#167
b1001 5
b11111100000000000000000000000000 /
b110111 $
b100000110010100000000000 &
#170
0!
#175
b0 *
b0 )
1"
#177
b101 .
b0 ,
b11111100000000000000000000000000 +
b1001 -
b110111 1
b100000110010100000000000 2
#180
0"
#185
b1010 0
1!
#187
b11111100000000000000000000000000 &
b101 '
b1010 5
bx /
#190
0!
#195
1"
#197
b11111100000000000000000000000000 2
b101 4
bx ,
bx +
b1010 -
bx *
bx )
#200
0"
#205
b1011 0
1!
#207
b1011 5
bx &
1(
#210
0!
#215
1"
#220
0"
#225
1!
#230
0!
#235
1"
#240
0"
#245
1!
#250
0!
#255
1"
#260
0"
#265
1!
#270
0!
#275
1"
#280
0"
b110 #
